amccrop.py
amccrop/__init__.py
amccrop/__main__.py
amccrop/amccrop.py
amc_cropper-0.0.5.dist-info/LICENSE.txt
amc_cropper-0.0.5.dist-info/METADATA
amc_cropper-0.0.5.dist-info/WHEEL
amc_cropper-0.0.5.dist-info/entry_points.txt
amc_cropper-0.0.5.dist-info/top_level.txt
amc_cropper-0.0.5.dist-info/RECORD
