Metadata-Version: 2.1
Name: amc-cropper
Version: 0.0.5
Summary: Crops AMC files to descired length based on provided fps, start, and end whole seconds. Works through command line.
Home-page: https://github.com/UomoCaffeLatte/AMCCrop
Author: Nikhil Reji
Author-email: Nikhil.Reji@live.co.uk
License: UNKNOWN
Platform: UNKNOWN
Classifier: Programming Language :: Python :: 3.6
Classifier: Programming Language :: Python :: 3.7
Classifier: License :: OSI Approved :: MIT License
Classifier: Natural Language :: English
Classifier: Topic :: Software Development :: Libraries
Requires-Dist: AsfAmc-Parser
